russound/__init__.py
russound/russound.py
russound/test_harness.py
russound-0.2.0.dist-info/LICENSE.txt
russound-0.2.0.dist-info/METADATA
russound-0.2.0.dist-info/WHEEL
russound-0.2.0.dist-info/top_level.txt
russound-0.2.0.dist-info/RECORD
