Metadata-Version: 2.1
Name: russound
Version: 0.2.0
Summary: Python API for select Russound RNET commands to provide Russound support within home-assistant.io
Home-page: https://github.com/laf/russound.git
Maintainer: Neil Lathwood
Maintainer-email: neil@lathwood.co.uk
Classifier: License :: OSI Approved :: GNU General Public License v3 (GPLv3)
License-File: LICENSE.txt
Requires-Dist: requests
